gears_cli/__init__.py
gears_cli/__main__.py
gears_cli-1.2.0.dist-info/entry_points.txt
gears_cli-1.2.0.dist-info/LICENSE
gears_cli-1.2.0.dist-info/WHEEL
gears_cli-1.2.0.dist-info/METADATA
gears_cli-1.2.0.dist-info/RECORD
