Metadata-Version: 2.1
Name: gears-cli
Version: 1.2.0
Summary: RedisGears cli
License: BSD-3-Clause
Author: RedisLabs
Author-email: oss@redislabs.com
Requires-Python: >=3.6,<4.0
Classifier: Development Status :: 4 - Beta
Classifier: Intended Audience :: Developers
Classifier: License :: OSI Approved :: BSD License
Classifier: Programming Language :: Python :: 3
Classifier: Programming Language :: Python :: 3.10
Classifier: Programming Language :: Python :: 3.6
Classifier: Programming Language :: Python :: 3.7
Classifier: Programming Language :: Python :: 3.8
Classifier: Programming Language :: Python :: 3.9
Classifier: Topic :: Database
Requires-Dist: click (>=8.0.1,<9.0.0)
Requires-Dist: redis (>=4.1.4,<5.0.0)
Project-URL: repository, https://github.com/RedisGears/gears-cli
Project-URL: url, https://redisai.io
